eq_api_connector/__init__.py
eq_api_connector/connector.py
eq_api_connector-1.0.0.dist-info/LICENSE
eq_api_connector-1.0.0.dist-info/METADATA
eq_api_connector-1.0.0.dist-info/WHEEL
eq_api_connector-1.0.0.dist-info/RECORD
