Metadata-Version: 2.3
Name: eq-api-connector
Version: 1.0.0
Summary: API connector (API SDK) to connect to public client app registrations using delegated permissions (MSAL).
License: MIT
Author: Åsmund Våge Fannemel
Author-email: asmf@equinor.com
Requires-Python: >=3.10,<4.0
Classifier: License :: OSI Approved :: MIT License
Classifier: Programming Language :: Python :: 3
Classifier: Programming Language :: Python :: 3.10
Classifier: Programming Language :: Python :: 3.11
Classifier: Programming Language :: Python :: 3.12
Classifier: Programming Language :: Python :: 3.13
Requires-Dist: msal-bearer (>=1.4.1,<2.0.0)
Requires-Dist: requests (>=2.32.5,<3.0.0)
